foundry/__init__.py
foundry/version.py
foundry/colours/__init__.py
foundry/colours/colours.py
foundry/files/__init__.py
foundry/files/files.py
foundry/games/__init__.py
foundry/games/menu.py
foundry/games/lottery/__init__.py
foundry/games/lottery/lottery.py
foundry/logger/__init__.py
foundry/logger/logger.py
foundry/menu/__init__.py
foundry/menu/keyhandler.py
foundry/menu/main_menu.py
foundry/menu/menu.py
luxforge_foundry-1.0.4.dist-info/METADATA
luxforge_foundry-1.0.4.dist-info/WHEEL
luxforge_foundry-1.0.4.dist-info/top_level.txt
luxforge_foundry-1.0.4.dist-info/RECORD
