Metadata-Version: 2.4
Name: luxforge-foundry
Version: 1.0.4
Summary: Audit-grade logging and modular tooling for LuxForge Foundry systems
Home-page: https://github.com/LuxForge/LuxForge-Foundry
Author: LuxForge
Author-email: LuxForge <lab@luxforge.dev>
License: MIT
Project-URL: Homepage, https://github.com/lux-forge/foundry
Project-URL: Repository, https://github.com/lux-forge/foundry
Project-URL: Issues, https://github.com/lux-forge/foundry/issues
Requires-Python: >=3.8
Requires-Dist: keyboard
Dynamic: author
Dynamic: home-page
Dynamic: requires-python
